callword/__init__.py
callword/callword.py
callword/english_words.txt
callword-0.11.dist-info/METADATA
callword-0.11.dist-info/WHEEL
callword-0.11.dist-info/top_level.txt
callword-0.11.dist-info/RECORD
