Metadata-Version: 2.1
Name: callword
Version: 0.11
Summary: represent phone numbers as easy to remember words
Home-page: http://github.com/bgheneti/callword
Author: Banti Gheneti
Author-email: banti@gheneti.com
License: MIT
Platform: UNKNOWN
Classifier: Programming Language :: Python :: 2.7
Classifier: Programming Language :: Python :: 3
Classifier: License :: OSI Approved :: MIT License
Classifier: Operating System :: OS Independent
